<Biome>
  <Topology 
    name="$biome_wandcave"
    type="BIOME_WANG_TILE"
    background_image="data/weather_gfx/background_wandcave.png"
    background_edge_right="data/biome_impl/wandcave/right_edge.png"
    background_edge_left="data/weather_gfx/edges/background_wandcave_left.png"
    background_edge_top="data/weather_gfx/edges/background_wandcave_top.png"
    background_edge_bottom="data/weather_gfx/edges/background_wandcave_bottom.png"
    background_edge_priority="11"     
    limit_background_image="0"
    wang_template_file="data/wang_tiles/wand.png" 
    lua_script="data/scripts/biomes/wandcave.lua"
    wang_map_width="256"
    wang_map_height="256"
    audio_ambience="wandcave"
  >
  <BitmapCaves 
      size_x="516"
      size_y="256"
      spawn_percent="0"
      blob_caves_count_min="0"
      blob_caves_count_max="1"
      blob_caves_radius_min="1"
      blob_caves_radius_max="1"
      blob_caves_strength_min="1.2"
      blob_caves_strength_max="2"
      cave_childs_min="0"
      cave_childs_max="1"
      cave_count_min="1"
      cave_count_max="2"
      cave_strength_min="0.2"
      cave_strength_max="1.8"
      mountain_count_min="0"
      mountain_count_max="0"
      mountain_size_min="1"
      mountain_size_max="10"
      surface_cave_childs_min="0"
      surface_cave_childs_max="0"
      surface_caves_count_min="0" 
      surface_caves_count_max="0"
	  >
    </BitmapCaves>
	
  </Topology>

  <Materials 
    name="wandcave" 
     >
    <!--
    <MaterialComponent 
      is_rare="0" 
      limit_max_y="2048" 
      limit_min_y="100" 
      limit_y="0" 
      material_index="10" 
      material_max="1.5" 
      material_min="1.0" 
      material_name="templeslab_static" 
      rare_polka_is_boxed="1" 
      rare_polka_probability="0.2" 
      rare_polka_radius_high="0.65" 
      rare_polka_radius_low="0.2" 
      rare_required_max="10" 
      rare_required_min="0.2" 
      rare_scale_x="0.05" 
      rare_scale_y="0.05" 
      rare_use_perlin="0" 
      rare_use_polka="1" >
    </MaterialComponent>
    -->
    <MaterialComponent 
      material_name="diamond" 
      is_rare="1" 
      limit_max_y="2048" 
      limit_min_y="100" 
      limit_y="0" 
      material_index="10" 
      material_max="1.2" 
      material_min="1.1" 
      rare_polka_is_boxed="1" 
      rare_polka_probability="0.757143" 
      rare_polka_radius_high="0.464286" 
      rare_polka_radius_low="0.1428571" 
      rare_required_max="10" 
      rare_required_min="0.371429" 
      rare_scale_x="0.0214286" 
      rare_scale_y="0.0214286" 
      rare_use_perlin="0" 
      rare_use_polka="1" >
    </MaterialComponent>

    <MaterialComponent 
      material_name="radioactive_liquid" 
      is_rare="1" 
      limit_max_y="2048" 
      limit_min_y="100" 
      limit_y="0" 
      material_index="10" 
      material_max="1.3" 
      material_min="1.0" 
      rare_polka_is_boxed="1" 
      rare_polka_probability="0.3" 
      rare_polka_radius_high="0.85" 
      rare_polka_radius_low="0.3" 
      rare_required_max="1" 
      rare_required_min="0.5" 
      rare_scale_x="0.01" 
      rare_scale_y="0.04" 
      rare_use_perlin="0" 
      rare_use_polka="1">
    </MaterialComponent>
	
	<MaterialComponent 
      material_name="templeslab_crumbling_static" 
      material_index="11" 
      material_max="3.5" 
      material_min="0.00006" 
      rare_polka_is_boxed="1" 
      rare_polka_probability="0.2" 
      rare_polka_radius_high="0.65" 
      rare_polka_radius_low="0.2" 
      rare_required_max="10" 
      rare_required_min="0.2" 
      rare_scale_x="0.05" 
      rare_scale_y="0.05" 
      rare_use_perlin="0" 
      rare_use_polka="1" >
    </MaterialComponent>

    <VegetationComponent 
      _enabled="1" 
      is_visual="1" 
      rand_seed="1248" 
      tree_extra_y="0" 
      tree_image_file="data/vegetation/vine_growth_1.xml" 
      tree_image_visual="" 
      tree_material="ceiling_plant_material" 
      tree_probability="0.24571" 
      tree_radius_high="0.635286" 
      tree_radius_low="0.146757" 
      tree_width="110.123" 
      visual_color="0x00b89f6c" 
      visual_offset_x="3" 
      visual_offset_y="0" 
      is_ceiling_plant="1"
      >
    </VegetationComponent>
	 <!--
    <VegetationComponent 
      _enabled="1" 
      is_visual="1" 
      rand_seed="4575" 
      tree_extra_y="0" 
      tree_image_file="data/vegetation/ceiling_vegetation_00$[2-8].png" 
      tree_image_visual="" 
      tree_material="ceiling_plant_material" 
      tree_probability="0.54571" 
      tree_radius_high="0.635286" 
      tree_radius_low="0.146757" 
      tree_width="11.123" 
      visual_color="0x00b89f6c" 
      visual_offset_x="3" 
      visual_offset_y="0" 
      is_ceiling_plant="1"
      >
    </VegetationComponent>
  -->
    <VegetationComponent 
      is_rare="1"
      is_visual="1"
      rand_seed="2431" 
      tree_extra_y="-1" 
      tree_image_file="data/vegetation/redplant_0$[1-4].xml" 
      tree_image_visual="" 
      tree_material="plant_material_red" 
      tree_probability="0.4" 
      tree_radius_high="0.2" 
      tree_radius_low="0.2" 
      tree_width="30" 
      visual_color="0xff4d5d44" 
      visual_offset_x="15" 
      visual_offset_y="32" 
    >
    </VegetationComponent>
	</Materials>
</Biome>

