<Sprite 
  filename="data/enemies_gfx/wolf.png" 
  offset_x="14" 
  offset_y="15" 
  default_animation="stand">

  <RectAnimation 
    frame_count="6" 
    frame_height="21" 
    frame_wait="0.1" 
    frame_width="29" 
    frames_per_row="8" 
    name="stand" 
    pos_x="0" 
    pos_y="1" 
    shrink_by_one_pixel="1" >

  </RectAnimation>

  <RectAnimation 
    frame_count="6" 
    frame_height="20" 
    frame_wait="0.1" 
    frame_width="28" 
    frames_per_row="8" 
    name="walk" 
    pos_x="0" 
    pos_y="22" >

    <Event 
      check_physics_material="1" 
      frame="2" 
      max_distance="500" 
      name="step" 
      on_finished="0" 
      probability="1" >

    </Event>

    <Event 
      check_physics_material="1" 
      frame="5" 
      max_distance="500" 
      name="step" 
      on_finished="0" 
      probability="1" >

    </Event>

  </RectAnimation>

  <RectAnimation 
    frame_count="6" 
    frame_height="20" 
    frame_wait="0.09" 
    frame_width="28" 
    frames_per_row="8" 
    name="swim_idle" 
    pos_x="0" 
    pos_y="22" >

    <Event 
      check_physics_material="0" 
      frame="2" 
      max_distance="500" 
      name="paddle" 
      on_finished="0" 
      probability="1" >

    </Event>

    <Event 
      check_physics_material="0" 
      frame="5" 
      max_distance="500" 
      name="paddle" 
      on_finished="0" 
      probability="1" >

    </Event>

  </RectAnimation>

  <RectAnimation 
    frame_count="6" 
    frame_height="20" 
    frame_wait="0.09" 
    frame_width="28" 
    frames_per_row="8" 
    name="swim_move" 
    pos_x="0" 
    pos_y="22" >

    <Event 
      check_physics_material="0" 
      frame="2" 
      max_distance="500" 
      name="paddle" 
      on_finished="0" 
      probability="1" >

    </Event>

    <Event 
      check_physics_material="0" 
      frame="5" 
      max_distance="500" 
      name="paddle" 
      on_finished="0" 
      probability="1" >

    </Event>

  </RectAnimation>

  <RectAnimation 
    frame_count="6" 
    frame_height="20" 
    frame_wait="0.07" 
    frame_width="28" 
    frames_per_row="8" 
    name="run" 
    pos_x="0" 
    pos_y="43" >

    <Event 
      check_physics_material="1" 
      frame="0" 
      max_distance="500" 
      name="step" 
      on_finished="0" 
      probability="1" >

    </Event>

    <Event 
      check_physics_material="1" 
      frame="5" 
      max_distance="500" 
      name="step" 
      on_finished="0" 
      probability="1" >

    </Event>

  </RectAnimation>

  <RectAnimation 
    frame_count="1" 
    frame_height="20" 
    frame_wait="0.07" 
    frame_width="28" 
    frames_per_row="8" 
    name="jump_up" 
    pos_x="0" 
    pos_y="64" >

    <Event 
      check_physics_material="1" 
      frame="0" 
      max_distance="500" 
      name="jump" 
      on_finished="0" 
      probability="1" >

    </Event>

  </RectAnimation>

  <RectAnimation 
    frame_count="1" 
    frame_height="20" 
    frame_wait="0.07" 
    frame_width="28" 
    frames_per_row="8" 
    name="jump_fall" 
    pos_x="0" 
    pos_y="64" >

  </RectAnimation>

  <RectAnimation 
    frame_count="1" 
    frame_height="20" 
    frame_wait="0.07" 
    frame_width="28" 
    frames_per_row="8" 
    name="attack_dash" 
    pos_x="0" 
    pos_y="64" >

    <Event 
      check_physics_material="0" 
      frame="0" 
      max_distance="500" 
      name="dash" 
      on_finished="0" 
      probability="1" >

    </Event>

  </RectAnimation>

  <RectAnimation 
    frame_count="6" 
    frame_height="21" 
    frame_wait="0.045" 
    frame_width="29" 
    frames_per_row="8" 
    loop="0" 
    name="attack" 
    pos_x="0" 
    pos_y="85" 
    shrink_by_one_pixel="1" >

    <Event 
      check_physics_material="0" 
      frame="3" 
      max_distance="500" 
      name="slash" 
      on_finished="0" 
      probability="1" >

    </Event>

  </RectAnimation>

  <RectAnimation 
    frame_count="4" 
    frame_height="20" 
    frame_wait="0.12" 
    frame_width="28" 
    frames_per_row="8" 
    loop="0" 
    name="lower_head" 
    pos_x="0" 
    pos_y="106" >

  </RectAnimation>

  <RectAnimation 
    frame_count="6" 
    frame_height="20" 
    frame_wait="0.1" 
    frame_width="28" 
    frames_per_row="8" 
    name="eat" 
    pos_x="0" 
    pos_y="127" >

    <Event 
      check_physics_material="0" 
      frame="2" 
      max_distance="500" 
      name="eat" 
      on_finished="0" 
      probability="1" >

    </Event>

  </RectAnimation>

  <RectAnimation 
    frame_count="4" 
    frame_height="20" 
    frame_wait="0.12" 
    frame_width="28" 
    frames_per_row="8" 
    loop="0" 
    name="raise_head" 
    pos_x="0" 
    pos_y="148" >

  </RectAnimation>

  <RectAnimation 
    frame_count="6" 
    frame_height="20" 
    frame_wait="0.1" 
    frame_width="28" 
    frames_per_row="8" 
    loop="0" 
    name="lie_down" 
    pos_x="0" 
    pos_y="169" >

  </RectAnimation>

  <RectAnimation 
    frame_count="2" 
    frame_height="20" 
    frame_wait="1.5" 
    frame_width="28" 
    frames_per_row="8" 
    loop="0" 
    name="sleep" 
    pos_x="0" 
    pos_y="190" >

  </RectAnimation>

  <RectAnimation 
    frame_count="5" 
    frame_height="20" 
    frame_wait="0.1" 
    frame_width="28" 
    frames_per_row="8" 
    loop="0" 
    name="rise_up" 
    pos_x="0" 
    pos_y="211" >

  </RectAnimation>

</Sprite>

